datastructpy/__init__.py
datastructpy/node.py
datastructpy/non_linear/trees/binary_search_tree.py
datastructpy-0.0.0.dist-info/LICENSE
datastructpy-0.0.0.dist-info/METADATA
datastructpy-0.0.0.dist-info/WHEEL
datastructpy-0.0.0.dist-info/RECORD
