Metadata-Version: 2.3
Name: datastructpy
Version: 0.0.0
Summary: Data Structures for Python
License: MIT
Author: Albert Halim
Requires-Python: >=3.11,<4.0
Classifier: License :: OSI Approved :: MIT License
Classifier: Programming Language :: Python :: 3
Classifier: Programming Language :: Python :: 3.11
Classifier: Programming Language :: Python :: 3.12
Classifier: Programming Language :: Python :: 3.13
Requires-Dist: sphinx-book-theme (>=1.1.3,<2.0.0)
